outliers_101703317/__init__.py
outliers_101703317/outliers.py
outliers_101703317-0.0.1.dist-info/LICENSE.txt
outliers_101703317-0.0.1.dist-info/METADATA
outliers_101703317-0.0.1.dist-info/WHEEL
outliers_101703317-0.0.1.dist-info/top_level.txt
outliers_101703317-0.0.1.dist-info/RECORD
